setup.py
distributions_ji/Binomialdistribution.py
distributions_ji/Gaussiandistribution.py
distributions_ji/Generaldistribution.py
distributions_ji/__init__.py
distributions_ji.egg-info/PKG-INFO
distributions_ji.egg-info/SOURCES.txt
distributions_ji.egg-info/dependency_links.txt
distributions_ji.egg-info/not-zip-safe
distributions_ji.egg-info/top_level.txt